odoo/addons/mail_restrict_follower_selection/README.rst
odoo/addons/mail_restrict_follower_selection/__init__.py
odoo/addons/mail_restrict_follower_selection/__manifest__.py
odoo/addons/mail_restrict_follower_selection/data/ir_actions.xml
odoo/addons/mail_restrict_follower_selection/data/ir_config_parameter.xml
odoo/addons/mail_restrict_follower_selection/i18n/de.po
odoo/addons/mail_restrict_follower_selection/i18n/en.po
odoo/addons/mail_restrict_follower_selection/i18n/fr.po
odoo/addons/mail_restrict_follower_selection/i18n/hr.po
odoo/addons/mail_restrict_follower_selection/i18n/it.po
odoo/addons/mail_restrict_follower_selection/i18n/mail_restrict_follower_selection.pot
odoo/addons/mail_restrict_follower_selection/i18n/sl.po
odoo/addons/mail_restrict_follower_selection/models/__init__.py
odoo/addons/mail_restrict_follower_selection/models/mail_followers.py
odoo/addons/mail_restrict_follower_selection/models/mail_thread.py
odoo/addons/mail_restrict_follower_selection/models/mail_wizard_invite.py
odoo/addons/mail_restrict_follower_selection/static/description/icon.png
odoo/addons/mail_restrict_follower_selection/tests/__init__.py
odoo/addons/mail_restrict_follower_selection/tests/test_mail_restrict_follower_selection.py
odoo11_addon_mail_restrict_follower_selection-11.0.2.0.1.dist-info/METADATA
odoo11_addon_mail_restrict_follower_selection-11.0.2.0.1.dist-info/WHEEL
odoo11_addon_mail_restrict_follower_selection-11.0.2.0.1.dist-info/top_level.txt
odoo11_addon_mail_restrict_follower_selection-11.0.2.0.1.dist-info/RECORD
