Metadata-Version: 2.1
Name: odoo11-addon-mail-restrict-follower-selection
Version: 11.0.2.0.1
Summary: Define a domain from which followers can be selected
Home-page: UNKNOWN
Author: Therp BV,Creu Blanca,Odoo Community Association (OCA)
Author-email: support@odoo-community.org
License: AGPL-3
Platform: UNKNOWN
Classifier: Programming Language :: Python
Classifier: Framework :: Odoo
Classifier: License :: OSI Approved :: GNU Affero General Public License v3
Requires-Python: >=2.7, !=3.0.*, !=3.1.*, !=3.2.*, !=3.3.*, !=3.4.*
Requires-Dist: odoo (<11.1dev,>=11.0a)
